{
  "version": "v2026.04.06",
  "release_date": "2026-04-06",
  "total_rows": 361200542,
  "total_size": 0,
  "tables": [
    {
      "name": "casts",
      "rows": 35644,
      "partitioned": false
    },
    {
      "name": "bottle",
      "rows": 895371,
      "partitioned": false
    },
    {
      "name": "bottle_measurement",
      "rows": 11135600,
      "partitioned": false
    },
    {
      "name": "cast_condition",
      "rows": 235513,
      "partitioned": false
    },
    {
      "name": "measurement_type",
      "rows": 104,
      "partitioned": false
    },
    {
      "name": "dataset",
      "rows": 5,
      "partitioned": false
    },
    {
      "name": "ctd_cast",
      "rows": 6065096,
      "partitioned": false
    },
    {
      "name": "ctd_measurement",
      "rows": 236782294,
      "partitioned": true
    },
    {
      "name": "ctd_summary",
      "rows": 104828768,
      "partitioned": true
    },
    {
      "name": "dic_sample",
      "rows": 4391,
      "partitioned": false
    },
    {
      "name": "dic_measurement",
      "rows": 16391,
      "partitioned": false
    },
    {
      "name": "dic_summary",
      "rows": 15786,
      "partitioned": false
    },
    {
      "name": "_spatial_attr",
      "rows": 40298,
      "partitioned": false
    },
    {
      "name": "_spatial",
      "rows": 3373,
      "partitioned": false
    },
    {
      "name": "cruise",
      "rows": 691,
      "partitioned": false
    },
    {
      "name": "grid",
      "rows": 218,
      "partitioned": false
    },
    {
      "name": "ichthyo",
      "rows": 830873,
      "partitioned": false
    },
    {
      "name": "lookup",
      "rows": 26,
      "partitioned": false
    },
    {
      "name": "net",
      "rows": 76512,
      "partitioned": false
    },
    {
      "name": "segment",
      "rows": 60413,
      "partitioned": false
    },
    {
      "name": "ship",
      "rows": 48,
      "partitioned": false
    },
    {
      "name": "site",
      "rows": 61104,
      "partitioned": false
    },
    {
      "name": "species",
      "rows": 1144,
      "partitioned": false
    },
    {
      "name": "taxa_rank",
      "rows": 41,
      "partitioned": false
    },
    {
      "name": "taxon",
      "rows": 3348,
      "partitioned": false
    },
    {
      "name": "tow",
      "rows": 75506,
      "partitioned": false
    },
    {
      "name": "invert_net",
      "rows": 7463,
      "partitioned": false
    },
    {
      "name": "invert",
      "rows": 23830,
      "partitioned": false
    },
    {
      "name": "cruise_summary",
      "rows": 691,
      "partitioned": false
    }
  ]
}
